[
  {
    "full_name": "open-sauced/open-sauced",
    "stargazers_count": 327,
    "open_issues_count": 24,
    "forks_count": 94
  },
  {
    "full_name": "cncf/sig-contributor-strategy",
    "stargazers_count": 36,
    "open_issues_count": 27,
    "forks_count": 12
  },
  {
    "full_name": "kubernetes/kubernetes",
    "stargazers_count": 73249,
    "open_issues_count": 2901,
    "forks_count": 26475
  },
  {
    "full_name": "cncf/sig-contributor-strategy",
    "stargazers_count": 36,
    "open_issues_count": 27,
    "forks_count": 12
  },
  {
    "full_name": "linkerd/linkerd2",
    "stargazers_count": 6396,
    "open_issues_count": 291,
    "forks_count": 685
  }
]