[
  {
    "full_name": "open-sauced/open-sauced",
    "stargazers_count": 335,
    "open_issues_count": 28,
    "forks_count": 96
  },
  {
    "full_name": "cncf/sig-contributor-strategy",
    "stargazers_count": 36,
    "open_issues_count": 28,
    "forks_count": 12
  },
  {
    "full_name": "kubernetes/kubernetes",
    "stargazers_count": 74008,
    "open_issues_count": 2927,
    "forks_count": 26809
  },
  {
    "full_name": "cncf/sig-contributor-strategy",
    "stargazers_count": 36,
    "open_issues_count": 28,
    "forks_count": 12
  },
  {
    "full_name": "linkerd/linkerd2",
    "stargazers_count": 6503,
    "open_issues_count": 271,
    "forks_count": 705
  }
]